aws_arns/__init__.py
aws_arns/_version.py
aws_arns/api.py
aws_arns/compat.py
aws_arns/constants.py
aws_arns/model.py
aws_arns/parse_arn.py
aws_arns/paths.py
aws_arns/resource.py
aws_arns/docs/__init__.py
aws_arns/srv/__init__.py
aws_arns/srv/apigateway.py
aws_arns/srv/athena.py
aws_arns/srv/awslambda.py
aws_arns/srv/batch.py
aws_arns/srv/bedrock.py
aws_arns/srv/cloud9.py
aws_arns/srv/cloudformation.py
aws_arns/srv/codebuild.py
aws_arns/srv/codecommit.py
aws_arns/srv/codepipeline.py
aws_arns/srv/dynamodb.py
aws_arns/srv/ec2.py
aws_arns/srv/ecr.py
aws_arns/srv/ecs.py
aws_arns/srv/efs.py
aws_arns/srv/eventbridge.py
aws_arns/srv/glue.py
aws_arns/srv/iam.py
aws_arns/srv/kinesis.py
aws_arns/srv/kms.py
aws_arns/srv/logs.py
aws_arns/srv/opensearch.py
aws_arns/srv/rds.py
aws_arns/srv/redshift.py
aws_arns/srv/s3.py
aws_arns/srv/sagemaker.py
aws_arns/srv/sagemaker_a2i.py
aws_arns/srv/secretmanager.py
aws_arns/srv/sns.py
aws_arns/srv/sqs.py
aws_arns/srv/ssm.py
aws_arns/srv/stepfunction.py
aws_arns/tests/__init__.py
aws_arns/tests/helper.py
aws_arns/tests/test_arns.py
aws_arns/vendor/__init__.py
aws_arns/vendor/pytest_cov_helper.py
aws_arns-1.5.1.dist-info/AUTHORS.rst
aws_arns-1.5.1.dist-info/LICENSE.txt
aws_arns-1.5.1.dist-info/METADATA
aws_arns-1.5.1.dist-info/WHEEL
aws_arns-1.5.1.dist-info/top_level.txt
aws_arns-1.5.1.dist-info/RECORD
